mycalc/calculator.py
whwnsgur230411-0.0.1.dist-info/METADATA
whwnsgur230411-0.0.1.dist-info/WHEEL
whwnsgur230411-0.0.1.dist-info/top_level.txt
whwnsgur230411-0.0.1.dist-info/RECORD
