Metadata-Version: 2.1
Name: whwnsgur230411
Version: 0.0.1
Summary: nice calc
Home-page: https://github.com/junhyeok0929/whwnsgur
Download-URL: https://github.com/junhyeok0929/whwnsgur
Author: whwnsgur
License: UNKNOWN
Platform: UNKNOWN
Classifier: Programming Language :: Python :: 3
